ponytail/__init__.py
ponytail-0.9.2.dist-info/LICENSE
ponytail-0.9.2.dist-info/METADATA
ponytail-0.9.2.dist-info/WHEEL
ponytail-0.9.2.dist-info/top_level.txt
ponytail-0.9.2.dist-info/RECORD
