Metadata-Version: 2.1
Name: ponytail
Version: 0.9.2
Summary: Python "tail -F" like functionality, targeted for processing log data, with a goal of being reliable and robust.
Home-page: https://github.com/linsomniac/ponytail
Author: Sean Reifschneider
Author-email: jafo00@gmail.com
Project-URL: Bug Tracker, https://github.com/linsomniac/ponytail/issues
Classifier: Programming Language :: Python :: 3
Classifier: License :: CC0 1.0 Universal (CC0 1.0) Public Domain Dedication
Classifier: Operating System :: OS Independent
Requires-Python: >=3.6
License-File: LICENSE
